dummy.py
dummy_lib-1.0.1.dist-info/METADATA
dummy_lib-1.0.1.dist-info/WHEEL
dummy_lib-1.0.1.dist-info/top_level.txt
dummy_lib-1.0.1.dist-info/RECORD
