Metadata-Version: 2.1
Name: dummy-lib
Version: 1.0.1
Summary: dummy Test Package
Home-page: UNKNOWN
Author: Droid
License: UNKNOWN
Platform: UNKNOWN
Classifier: Programming Language :: Python :: 3
Classifier: License :: OSI Approved :: MIT License
Classifier: Operating System :: OS Independent
Requires-Python: >=3.6
